spacy_layout/__init__.py
spacy_layout/layout.py
spacy_layout/types.py
spacy_layout/util.py
spacy_layout-0.0.12.dist-info/LICENSE
spacy_layout-0.0.12.dist-info/METADATA
spacy_layout-0.0.12.dist-info/WHEEL
spacy_layout-0.0.12.dist-info/top_level.txt
spacy_layout-0.0.12.dist-info/zip-safe
spacy_layout-0.0.12.dist-info/RECORD
