Metadata-Version: 2.2
Name: spacy_layout
Version: 0.0.12
Summary: Use spaCy with PDFs, Word docs and other documents
Home-page: https://github.com/explosion/spacy-layout
Author: Explosion
Author-email: contact@explosion.ai
License: MIT
Project-URL: Release notes, https://github.com/explosion/spacy-layout/releases
Project-URL: Source, https://github.com/explosion/spacy-layout
Classifier: Development Status :: 4 - Beta
Classifier: Environment :: Console
Classifier: Intended Audience :: Developers
Classifier: Intended Audience :: Science/Research
Classifier: License :: OSI Approved :: MIT License
Classifier: Operating System :: POSIX :: Linux
Classifier: Operating System :: MacOS :: MacOS X
Classifier: Operating System :: Microsoft :: Windows
Classifier: Programming Language :: Python :: 3
Classifier: Programming Language :: Python :: 3.10
Classifier: Programming Language :: Python :: 3.11
Classifier: Programming Language :: Python :: 3.12
Classifier: Topic :: Scientific/Engineering
Requires-Python: >=3.10
License-File: LICENSE
Requires-Dist: spacy>=3.7.5
Requires-Dist: docling>=2.5.2
Requires-Dist: pandas
Requires-Dist: srsly
